<manifest alg="2" build="2018.1.0.386" opt="false" iceEnabled="true" iceMarkupVersion="2" iceEnabledOptions="link,responsive,cachebuster,textStyling" exportTarget="other" domain="33234343.com" resolutions="1x" timestamp="1576791149584">
  <folder name="css">
    <file name="site_global.css" crc="444006867"/>
    <file name="index.css" crc="315624690" ref="index"/>
    <file name="nomq_index.css" crc="35570241" ref="index"/>
  </folder>
  <folder name="scripts">
    <file name="jquery-1.8.3.min.js" crc="209076791" ref="index"/>
    <file name="museutils.js" crc="340535759" ref="index"/>
    <file name="whatinput.js" crc="86476730" ref="index"/>
    <file name="museconfig.js" crc="4286661555" ref="index"/>
    <file name="jquery.watch.js" crc="51536988" ref="index"/>
    <file name="webpro.js" crc="4059564322" ref="index"/>
    <file name="musewpslideshow.js" crc="3862962738" ref="index"/>
    <file name="jquery.museoverlay.js" crc="4147669564" ref="index"/>
    <file name="touchswipe.js" crc="4075097462" ref="index"/>
    <file name="jquery.museresponsive.js" crc="527716135" ref="index"/>
    <file name="require.js" crc="7928878" ref="index"/>
  </folder>
  <folder name="images">
    <file name="u674-4.png" crc="323573042" ref="index"/>
    <file name="hat2.png" crc="357396617" seo="true" ref="index">
      <caption webpage="index" alt=""/>
      <caption webpage="index" alt=""/>
      <caption webpage="index" alt=""/>
      <caption webpage="index" alt=""/>
    </file>
    <file name="blank.gif" crc="4208392903" ref="index"/>
    <file name="hat1.png" crc="4006528517" seo="true" ref="index">
      <caption webpage="index" alt=""/>
      <caption webpage="index" alt=""/>
      <caption webpage="index" alt=""/>
      <caption webpage="index" alt=""/>
    </file>
    <file name="hat3.png" crc="469155716" seo="true" ref="index">
      <caption webpage="index" alt=""/>
      <caption webpage="index" alt=""/>
      <caption webpage="index" alt=""/>
      <caption webpage="index" alt=""/>
    </file>
    <file name="hat4.png" crc="152294985" seo="true" ref="index">
      <caption webpage="index" alt=""/>
      <caption webpage="index" alt=""/>
      <caption webpage="index" alt=""/>
      <caption webpage="index" alt=""/>
    </file>
    <file name="hat5.png" crc="449751533" seo="true" ref="index">
      <caption webpage="index" alt=""/>
      <caption webpage="index" alt=""/>
      <caption webpage="index" alt=""/>
      <caption webpage="index" alt=""/>
    </file>
    <file name="hat6.png" crc="4163635328" seo="true" ref="index">
      <caption webpage="index" alt=""/>
      <caption webpage="index" alt=""/>
      <caption webpage="index" alt=""/>
      <caption webpage="index" alt=""/>
    </file>
    <file name="hat7.png" crc="273481989" seo="true" ref="index">
      <caption webpage="index" alt=""/>
      <caption webpage="index" alt=""/>
      <caption webpage="index" alt=""/>
      <caption webpage="index" alt=""/>
    </file>
    <file name="hat8.png" crc="3785136964" seo="true" ref="index">
      <caption webpage="index" alt=""/>
      <caption webpage="index" alt=""/>
      <caption webpage="index" alt=""/>
      <caption webpage="index" alt=""/>
    </file>
    <file name="hat9.png" crc="446971648" seo="true" ref="index">
      <caption webpage="index" alt=""/>
      <caption webpage="index" alt=""/>
      <caption webpage="index" alt=""/>
      <caption webpage="index" alt=""/>
    </file>
    <file name="hat10.png" crc="130108323" seo="true" ref="index">
      <caption webpage="index" alt=""/>
      <caption webpage="index" alt=""/>
      <caption webpage="index" alt=""/>
      <caption webpage="index" alt=""/>
    </file>
    <file name="hat11.png" crc="3839504408" seo="true" ref="index">
      <caption webpage="index" alt=""/>
      <caption webpage="index" alt=""/>
      <caption webpage="index" alt=""/>
      <caption webpage="index" alt=""/>
    </file>
    <file name="hat12.png" crc="522784047" seo="true" ref="index">
      <caption webpage="index" alt=""/>
      <caption webpage="index" alt=""/>
      <caption webpage="index" alt=""/>
      <caption webpage="index" alt=""/>
    </file>
    <file name="hat13.png" crc="4012977777" seo="true" ref="index">
      <caption webpage="index" alt=""/>
      <caption webpage="index" alt=""/>
      <caption webpage="index" alt=""/>
      <caption webpage="index" alt=""/>
    </file>
    <file name="hat14.png" crc="4114297907" seo="true" ref="index">
      <caption webpage="index" alt=""/>
      <caption webpage="index" alt=""/>
      <caption webpage="index" alt=""/>
      <caption webpage="index" alt=""/>
    </file>
    <file name="hat15.png" crc="3880068106" seo="true" ref="index">
      <caption webpage="index" alt=""/>
      <caption webpage="index" alt=""/>
      <caption webpage="index" alt=""/>
      <caption webpage="index" alt=""/>
    </file>
    <file name="hat16.png" crc="384378436" seo="true" ref="index">
      <caption webpage="index" alt=""/>
      <caption webpage="index" alt=""/>
      <caption webpage="index" alt=""/>
      <caption webpage="index" alt=""/>
    </file>
    <file name="19.png" crc="510618516" seo="true" ref="index">
      <caption webpage="index" alt=""/>
      <caption webpage="index" alt=""/>
      <caption webpage="index" alt=""/>
      <caption webpage="index" alt=""/>
    </file>
    <file name="hat17.png" crc="3839830994" seo="true" ref="index">
      <caption webpage="index" alt=""/>
      <caption webpage="index" alt=""/>
      <caption webpage="index" alt=""/>
      <caption webpage="index" alt=""/>
    </file>
    <file name="hat18.png" crc="4123948031" seo="true" ref="index">
      <caption webpage="index" alt=""/>
      <caption webpage="index" alt=""/>
      <caption webpage="index" alt=""/>
      <caption webpage="index" alt=""/>
    </file>
    <file name="u667-4.png" crc="288607286" ref="index"/>
    <file name="loading.gif" crc="3815509949" ref="index"/>
    <file name="u979-4.png" crc="404005467" ref="index"/>
    <file name="1_2.png" crc="250992316" seo="true" ref="index">
      <caption webpage="index" alt=""/>
      <caption webpage="index" alt=""/>
      <caption webpage="index" alt=""/>
      <caption webpage="index" alt=""/>
    </file>
    <file name="1_3.png" crc="123098122" seo="true" ref="index">
      <caption webpage="index" alt=""/>
      <caption webpage="index" alt=""/>
      <caption webpage="index" alt=""/>
      <caption webpage="index" alt=""/>
    </file>
    <file name="1_4.png" crc="131227483" seo="true" ref="index">
      <caption webpage="index" alt=""/>
      <caption webpage="index" alt=""/>
      <caption webpage="index" alt=""/>
      <caption webpage="index" alt=""/>
    </file>
    <file name="1_5.png" crc="4004175652" seo="true" ref="index">
      <caption webpage="index" alt=""/>
      <caption webpage="index" alt=""/>
      <caption webpage="index" alt=""/>
      <caption webpage="index" alt=""/>
    </file>
    <file name="1_6.png" crc="311106345" seo="true" ref="index">
      <caption webpage="index" alt=""/>
      <caption webpage="index" alt=""/>
      <caption webpage="index" alt=""/>
      <caption webpage="index" alt=""/>
    </file>
    <file name="1_7.png" crc="3838103014" seo="true" ref="index">
      <caption webpage="index" alt=""/>
      <caption webpage="index" alt=""/>
      <caption webpage="index" alt=""/>
      <caption webpage="index" alt=""/>
    </file>
    <file name="1_8.png" crc="3865156539" seo="true" ref="index">
      <caption webpage="index" alt=""/>
      <caption webpage="index" alt=""/>
      <caption webpage="index" alt=""/>
      <caption webpage="index" alt=""/>
    </file>
    <file name="1_9.png" crc="14826458" seo="true" ref="index">
      <caption webpage="index" alt=""/>
      <caption webpage="index" alt=""/>
      <caption webpage="index" alt=""/>
      <caption webpage="index" alt=""/>
    </file>
    <file name="1_10.png" crc="4081485851" seo="true" ref="index">
      <caption webpage="index" alt=""/>
      <caption webpage="index" alt=""/>
      <caption webpage="index" alt=""/>
      <caption webpage="index" alt=""/>
    </file>
    <file name="1_11.png" crc="4261394997" seo="true" ref="index">
      <caption webpage="index" alt=""/>
      <caption webpage="index" alt=""/>
      <caption webpage="index" alt=""/>
      <caption webpage="index" alt=""/>
    </file>
    <file name="1_12.png" crc="4082898278" seo="true" ref="index">
      <caption webpage="index" alt=""/>
      <caption webpage="index" alt=""/>
      <caption webpage="index" alt=""/>
      <caption webpage="index" alt=""/>
    </file>
    <file name="1_14.png" crc="3777222486" seo="true" ref="index">
      <caption webpage="index" alt=""/>
      <caption webpage="index" alt=""/>
      <caption webpage="index" alt=""/>
      <caption webpage="index" alt=""/>
    </file>
    <file name="1_15.png" crc="3787426656" seo="true" ref="index">
      <caption webpage="index" alt=""/>
      <caption webpage="index" alt=""/>
      <caption webpage="index" alt=""/>
      <caption webpage="index" alt=""/>
    </file>
    <file name="sonc.png" crc="4041949931" seo="true" ref="index">
      <caption webpage="index" alt=""/>
      <caption webpage="index" alt=""/>
      <caption webpage="index" alt=""/>
      <caption webpage="index" alt=""/>
    </file>
    <file name="1_13.png" crc="3785003370" seo="true" ref="index">
      <caption webpage="index" alt=""/>
      <caption webpage="index" alt=""/>
      <caption webpage="index" alt=""/>
      <caption webpage="index" alt=""/>
    </file>
    <file name="u981-4.png" crc="3769083649" ref="index"/>
    <file name="u1021-4.png" crc="218950844" ref="index"/>
    <file name="2_1.png" crc="3900686450" seo="true" ref="index">
      <caption webpage="index" alt=""/>
      <caption webpage="index" alt=""/>
      <caption webpage="index" alt=""/>
      <caption webpage="index" alt=""/>
    </file>
    <file name="2_2.png" crc="3902767173" seo="true" ref="index">
      <caption webpage="index" alt=""/>
      <caption webpage="index" alt=""/>
      <caption webpage="index" alt=""/>
      <caption webpage="index" alt=""/>
    </file>
    <file name="botl.png" crc="3833236934" seo="true" ref="index">
      <caption webpage="index" alt=""/>
      <caption webpage="index" alt=""/>
      <caption webpage="index" alt=""/>
      <caption webpage="index" alt=""/>
    </file>
    <file name="elf.png" crc="4096859439" seo="true" ref="index">
      <caption webpage="index" alt=""/>
      <caption webpage="index" alt=""/>
      <caption webpage="index" alt=""/>
      <caption webpage="index" alt=""/>
    </file>
    <file name="2_3.png" crc="3950418171" seo="true" ref="index">
      <caption webpage="index" alt=""/>
      <caption webpage="index" alt=""/>
      <caption webpage="index" alt=""/>
      <caption webpage="index" alt=""/>
    </file>
    <file name="u1023-4.png" crc="4220246160" ref="index"/>
    <file name="обложк-crop-u2297.png" crc="481790115" seo="true" ref="index">
      <caption webpage="index" alt=""/>
    </file>
    <file name="simple.png" crc="6770582" seo="true" ref="index">
      <caption webpage="index" alt=""/>
      <caption webpage="index" alt=""/>
      <caption webpage="index" alt=""/>
      <caption webpage="index" alt=""/>
    </file>
    <file name="yo.jpg" crc="188872728" seo="true" ref="index">
      <caption webpage="index" alt=""/>
      <caption webpage="index" alt=""/>
      <caption webpage="index" alt=""/>
    </file>
    <file name="иконка.jpg" crc="206350472" seo="true" ref="index">
      <caption webpage="index" alt=""/>
      <caption webpage="index" alt=""/>
      <caption webpage="index" alt=""/>
      <caption webpage="index" alt=""/>
    </file>
    <file name="u674-42.png" crc="1093417" ref="index"/>
    <file name="u667-42.png" crc="299297598" ref="index"/>
    <file name="u979-42.png" crc="4190685343" ref="index"/>
    <file name="u981-42.png" crc="155911966" ref="index"/>
    <file name="u1021-42.png" crc="4266349234" ref="index"/>
    <file name="u1023-42.png" crc="3896771249" ref="index"/>
    <file name="обложк-crop-u22972.png" crc="7572533" seo="true" ref="index">
      <caption webpage="index" alt=""/>
    </file>
    <file name="u674-43.png" crc="4019887310" ref="index"/>
    <file name="u667-43.png" crc="165897168" ref="index"/>
    <file name="u979-43.png" crc="4065853787" ref="index"/>
    <file name="u981-43.png" crc="302460948" ref="index"/>
    <file name="u1021-43.png" crc="101290771" ref="index"/>
    <file name="u1023-43.png" crc="4022691178" ref="index"/>
    <file name="обложк-crop-u22973.png" crc="4090457973" seo="true" ref="index">
      <caption webpage="index" alt=""/>
    </file>
    <file name="u674-44.png" crc="3860392612" ref="index"/>
    <file name="u667-44.png" crc="3903792776" ref="index"/>
    <file name="u979-44.png" crc="4215161565" ref="index"/>
    <file name="u981-44.png" crc="49499031" ref="index"/>
    <file name="u1021-44.png" crc="20907027" ref="index"/>
    <file name="u1023-44.png" crc="3819670045" ref="index"/>
    <file name="обложк-crop-u22974.png" crc="4024083093" seo="true" ref="index">
      <caption webpage="index" alt=""/>
    </file>
    <file name="yo-crop-u2372.jpg" crc="100722328" seo="true" ref="index">
      <caption webpage="index" alt=""/>
    </file>
  </folder>
  <file name="index.html" crc="3904159368" seo="true" mt="1576784226870" redirect="true"/>
</manifest>